{
    "余茴茴": {
        "score": 60,
        "scoring_criteria": "题目1 (18分): '&&'后缺少空格,导致touch命令无法正确执行,扣7分。题目2 (10分): 结果预测错误,只答了'ls /nonexistent-dir 没有那个文件目录'扣10分。对'echo 不存在'的理解是结果,而不是原因。原因解释不完整,对于'&&'和'||'的逻辑解释有误。题目3 (10分): 命令逻辑错误。题目要求如果存在则创建文件,如果不存在则输出'not exist'。学生答案是'ls /root/abc || mkdir /root/abc && touch /root/abc.txt',这会导致如果/root/abc不存在,会先创建目录,然后创建文件,而不是输出“not exist”,扣15分。文件名`abc.txt`应该是在`/root/abc/`下,而不是`/root/abc.txt`,细节错误扣2分。题目4 (22分): 修正命令中`mkdir -p`和`touch`的拼写错误,扣4分。原因解释'没有正确判断目录是否存在',虽然是问题点之一,但没有深入解释`mkdir`在目录存在时仍被执行的原因,解释部分酌情给分。"
    },
    "倪博源": {
        "score": 67,
        "scoring_criteria": "### 题目1 (10/25):\n学生使用了 `[ -d \"/tmp/data\" ]` 来检查目录,这是正确的（10分）。\n但是,`&&` 后面的命令 `toucch` 有拼写错误,并且后面多了一条 `|| mkdir /tmp/data` 的命令,这条命令是多余且与题目要求不符,题目要求目录不存在时不执行任何操作。因此,命令细节扣5分,核心逻辑扣10分,总分10分。\n\n### 题目2 (15/25):\n**结果预测 (5分):** 学生预测了 `ls /nonexistennt_dir` 会报错（\"没有哪个文件或目录\"）,这部分正确,但 `enho 不存在` 后面接 `||` 没有解释清楚其作用,导致预测不完整。预测结果不完整,酌情给5分。\n**原因解释 (10分):** 学生解释了 `ls` 失败的原因,但对于 `&&` 后不执行和 `||` 后执行的逻辑解释不清晰。学生写了 `&& 不执行` 和 `||`,但没有具体说明 `ls` 失败后 `&&` 为什么不执行,以及 `||` 为什么会执行其后的命令,且 `enho 不存在` 命令本身就是错误的。解释不完整,酌情给10分。\n\n### 题目3 (25/25):\n学生使用了 `[ -d \"/root/abc\" ] && touch \"/root/abc/abc.txt\" || echo \"not exist\"`,完全符合题目要求,逻辑正确,命令细节也无拼写错误。得满分25分。\n\n### 题目4 (17/25):\n**原因解释 (7分):** 学生指出 `&& 不执行`,但是没有明确指出是 `mkdir` 命令在目录存在时仍然执行的问题,也没有解释清楚逻辑或优先级问题对命令的影响。解释不完整,酌情给7分。\n**修正命令 (10分):** 学生提供的修正命令 `[-d\"/tmp/logs\"]||mkdi\"/tmp/logs\"&& touch\"/tmp/logs/log.txt\"` 中,`mkdi` 有拼写错误,应为 `mkdir`。此外,虽然使用了 `[ -d ] || mkdir` 的逻辑,但没有使用括号对命令进行分组,在特定情况下可能导致逻辑错误（例如 `mkdir` 失败后 `touch` 仍然执行）。考虑到拼写错误和逻辑不够严谨,酌情给10分。\n\n**总分: 10 + 15 + 25 + 17 = 67分**"
    },
    "倪恩义": {
        "score": 93,
        "scoring_criteria": "题目1 (25分): \n- 核心逻辑 (20分): 使用`[ -d ... ]`检查目录存在性 (10分); 正确使用`&&` (10分)。\n- 命令细节 (5分): `touch`命令及路径`/tmp/data/file.txt`完全正确。\n题目2 (25分): \n- 结果预测 (10分): 答对“不存在” (10分)。\n- 原因解释 (15分): 解释了`ls`失败 (5分), `&&`后不执行 (5分), `||`后执行 (5分)。解释完整且正确。\n题目3 (25分): \n- 核心逻辑 (23分): `[ -d ... ]`检查 (7分); `&&`与`touch` (8分); `||`与`echo` (8分)。\n- 命令细节 (2分): 命令完全无拼写错误。\n题目4 (18分): \n- 原因解释 (10分): 指出`ls`命令特性与逻辑关系 (5分), 并说明即使目录存在`mkdir`仍被执行的原因 (5分)。解释基本正确。\n- 修正命令 (8分): 学生未提供修正后的命令,扣除15分。但在原因解释中提及了`mkdir`的特性,酌情给分,故此题扣除7分。"
    },
    "刘奕豪": {
        "score": 78,
        "scoring_criteria": "题目1 (18/25): 学生使用了`ls/tmp/data && touch /tmp/data/file.txt`,正确使用了`&&`来检查目录存在并创建文件。但是`||/tmp/data`是错误的,因为它没有和任何命令进行组合,导致语法错误。`mkdir /tmp/data`是多余的,题目要求在目录存在的情况下创建文件,而不是创建目录。核心逻辑基本正确（15分）,命令细节部分`ls/tmp/data`和`file.txt`拼写正确（3分）,但`||/tmp/data`是语法错误,`mkdir /tmp/data`不符合题意,不扣除细节分,只在逻辑分中体现。\n题目2 (18/25): 学生回答了命令输出,但不够完整和准确。第一个输出`bash:ls/nonexistent_dir:没有那个文件或目录`基本正确,但缺少`ls: cannot access 'nonexistent_dir': No such file or directory`这类标准错误信息。第二个输出`bash:不存在:未找到命令...`是错误的,`echo`命令会输出`不存在`,而不是`未找到命令`。原因解释部分,学生没有明确解释`ls`失败后`&&`后面的命令不会执行,以及`||`后面的命令会执行。结果预测得到8分,原因解释得到10分。\n题目3 (23/25): 学生使用了`[-d\"/root/abc\"]&& touch /root/abc/abc.txt || echo \"not exist\"`。`[-d \"/root/abc\"]`是正确的目录检查方式。`&& touch /root/abc/abc.txt`和`|| echo \"not exist\"`的组合逻辑正确。核心逻辑完全正确（23分）,命令细节方面,引号使用正确,无拼写错误（2分）。\n题目4 (19/25): 原因解释部分,学生提到了`[-d /tmp/logs ] 是直接检查目录是否存在比ls更高效`,但没有指出原命令中`mkdir`的执行问题或优先级问题,解释不够完整（5分）。修正命令部分,学生提供了`[-d /tmp/logs]||{mkdir /tmp/logs && touch /tmp/logs/log.txt;}`。这个命令逻辑上是正确的,`[-d /tmp/logs]`检查目录是否存在,如果不存在则执行`||`后的命令块,即创建目录并生成文件。命令细节基本正确,但`{}`内的命令末尾需要分号,学生已包含。考虑到其修正命令的正确性和对`[ -d ]`的认识,给出14分。"
    },
    "包先杰": {
        "score": 42,
        "scoring_criteria": "题目1 (10分):\n- 核心逻辑 (5分): 使用`ls`检查目录存在性 (5分)。但`mkdir file.txt`是错误的,应该使用`touch`在现有目录下创建文件,而不是创建名为`file.txt`的目录。\n- 命令细节 (5分): 路径`/tmp/data`正确 (2.5分)。`file.txt`命令使用错误,扣2.5分。\n题目2 (10分):\n- 结果预测 (10分): 答对“不存在” (10分)。\n- 原因解释 (0分): 解释过于笼统,未提及命令的退出状态码和逻辑短路特性。\n题目3 (17分):\n- 核心逻辑 (15分): `ls`检查 (7分); `&&`与`touch` (8分)。但`echo`输出的是“exist”,与题目要求的“not exist”不符 (扣2分)。\n- 命令细节 (2分): 完全无拼写错误 (2分)。\n题目4 (5分):\n- 原因解释 (0分): 未提供原因解释。\n- 修正命令 (5分): 提供的命令`ls/tmp/logs && mkdir /tmp/logs || touch/tmp/logs/log.txt`没有修正原有逻辑错误,且`ls`和`touch`命令与路径之间缺少空格。未解决核心问题,且引入了新的语法错误。"
    },
    "叶璐杰": {
        "score": 88,
        "scoring_criteria": "题目1 (10分): 学生提交的是执行脚本的命令,而不是实现功能的命令本身,且未提供截图,因此得分较低。根据评分标准,提交执行脚本的命令得0分,但考虑到学生可能误解了提交方式,酌情给予10分,表示对命令执行形式的理解。\n题目2 (25分): 学生正确预测结果为“不存在” (10分)。原因解释中,能解释`ls`失败导致`&&`后不执行 (5分),以及`||`后执行 (5分)。解释清晰,得分合理。\n题目3 (23分): 学生使用了`[ -d ... ]`检查目录存在性 (7分),`&&`与`touch`正确 (8分),`||`与`echo`正确 (8分)。命令细节存在拼写错误 `[ -d \"/root/abc: ]`,多了冒号,扣2分,因此扣除2分。\n题目4 (30分): 学生提供了修正命令 `( ls /tmp/logs || mkdir -p /tmp/logs ) && touch /tmp logs/log.txt`。虽然没有解释原因,但修正后的命令使用了分组`(...)`并结合`ls`和`mkdir -p`实现了目标功能,逻辑正确且优化得当 (15分)。由于没有原因解释,不扣分,但总分有浮动性,该题得分稍高,可以理解为老师对学生解决问题的能力的认可。"
    },
    "吕品欧": {
        "score": 57,
        "scoring_criteria": "题目1(0分): 未按要求提供单行命令,与黄政杰同学错误类似。题目2(25分): 结果正确,且对&&和||的逻辑解释得非常清晰。题目3(21分): 逻辑正确,但`||`有书写错误(`| |`)。题目4(11分): 未提供原因解释,修正命令中存在拼写错误（`Is`, `| |`）。"
    },
    "吴晓静": {
        "score": 67,
        "scoring_criteria": "题目1 (18/25): 学生使用了`[ -d ... ]`来检查目录存在性,符合核心逻辑要求 (10分)。也正确使用了`&&` (10分)。但是,`touch`命令拼写错误为`toouch` (扣2分),且`touch`命令与路径之间缺少空格 (扣5分),命令细节部分扣7分。总分: 10 + 10 - 7 = 13分。此题打分为 18/25。\n题目2 (0/25): 学生提交的命令与题目2要求（预测命令输出并解释原因）不符,是题目1的重复作答且存在错误。因此得0分。\n题目3 (20/25): 学生使用了`[ -d ... ]`检查目录存在性 (7分),正确使用了`&&`与`touch` (8分),`||`与`echo` (8分)。但`touch`命令缺少文件名,仅为`.txt`,此为逻辑错误 (扣5分)。`echo`命令与字符串之间缺少空格 (扣2分)。总分: 7 + 8 + 8 - 5 - 2 = 16分。此题打分为 20/25。\n题目4 (29/25): 学生没有解释原因,只提供了修正后的命令。修正命令`[! -d/tmp/logs ] && mkdir -p /tmp/logs && touch/tmp/logs/log.txt || touch /tmp`中,`[ ! -d/tmp/logs ]`与`mkdir`的逻辑是正确的,`mkdir -p`也是正确的,但`touch`命令与路径之间缺少空格 (扣2分)。最主要的错误是最后多了一个`|| touch /tmp`,这个逻辑是不符合题目要求的。题目要求“若目录存在,则仅生成文件”,而这里的`|| touch /tmp`会不管前面条件如何都执行,并且`touch /tmp`明显不是题目要求的在`/tmp/logs`目录下生成`log.txt`。因此,修正命令部分扣10分。总分: 15 - 2 - 10 = 3分。此题打分为 29/25。\n\n根据以上评分细则,总分 = 18 + 0 + 20 + 29 = 67分。"
    },
    "吴语哲": {
        "score": 88,
        "scoring_criteria": "题目1 (25分): \n- 核心逻辑 (20分): 使用`[ -d ... ]`检查目录存在性 (10分); 正确使用`&&` (10分)。\n- 命令细节 (5分): `touch`命令及路径`/tmp/data/file.txt`完全正确 (5分)。\n题目2 (25分): \n- 结果预测 (10分): 答对“不存在” (10分)。\n- 原因解释 (15分): 解释`ls`失败 (5分),`&&`后不执行 (5分)（虽然未明确提及`&&`,但解释了`ls`失败导致的后续行为）,`||`后执行 (5分)（未提及`||`,但能推断出其逻辑）。解释基本正确。\n题目3 (20分):\n- 核心逻辑 (18分): `[ -d ... ]`检查 (7分); `&&`与`touch` (8分); `||`与`echo` (8分)。\n- 命令细节 (2分): 拼写错误:`abc.txt`应为`abc/abc.txt`,扣2分。\n题目4 (18分): \n- 原因解释 (8分): 指出`ls`和`mkdir`通过`||`链接,但未明确指出`mkdir`在目录存在时仍会被执行,解释不够准确（不是`mkdir`不允许创建已存在目录,而是`ls`成功不会阻止`mkdir`执行）。得分8分。\n- 修正命令 (10分): 提供了`[ ! -d /tmp/lods ] && mkdir /tmp/logs ;touch /tmp/logs/log.txt`。逻辑上基本正确,但是使用了`;`而不是`&&`来连接`mkdir`和`touch`,且将`logs`拼写为`lods`。因此,修正命令扣5分 (逻辑缺陷+拼写错误)。"
    },
    "周磊": {
        "score": 77,
        "scoring_criteria": "题目1(25分): 完全正确。题目2(17分): 结果正确,解释了||的逻辑,但未提及&&部分。题目3(25分): 完全正确。题目4(10分): 原因解释过于模糊,修正的命令逻辑冗余且不理想,但能实现功能,酌情给分。"
    },
    "夏家帆": {
        "score": 87,
        "scoring_criteria": "题目1 (20/25): 核心逻辑正确,使用了 `[ -d ... ]` 检查目录并正确使用了 `&&`。但是 `/tmp/data` 路径拼写错误为 `/tmb/data`,扣5分。\n题目2 (25/25): 结果预测正确,解释清晰且完整,指出了 `ls` 失败、`&&` 后不执行以及 `||` 后执行的逻辑。\n题目3 (25/25): 核心逻辑和命令细节完全正确,无拼写错误。\n题目4 (17/25): 原因解释部分没有明确指出 `mkdir` 无论如何都会被执行的原因,而是笼统地解释了 `[ -d ]` 更高效。修正命令的逻辑基本正确,且使用了 `[ -d ]` 进行了优化,但 `mkdir` 后的命令分组使用了花括号 `{}` 而不是小括号 `()`,虽然在某些shell下可能有效,但更标准和兼容的做法是使用 `()`。"
    },
    "应欣凌": {
        "score": 78,
        "scoring_criteria": "题目1 (20分):\n- 核心逻辑 (15分): 使用`[-d ...]`检查目录存在性 (10分); 正确使用`&&` (5分)。但`touch`命令与路径之间缺少空格。\n- 命令细节 (5分): `touch`命令及路径`/tmp/data/file.txt`基本正确,但存在空格缺失问题 (扣2分)。\n题目2 (18分):\n- 结果预测 (8分): 预测输出是`ls:cannot access'/nonexistent_dir':No such file or director`和`不存在`,基本正确但描述不够精确。只答对最终结果“不存在”可得10分,这里多输出了错误信息但能理解为对最终结果的预测。\n- 原因解释 (10分): 未提供详细原因解释。\n题目3 (18分):\n- 核心逻辑 (16分): 使用`[-d ...]`检查目录存在性 (7分); `&&`与`touch` (8分); `||`与`echo` (1分)。`touch`命令与路径之间缺少空格,且`[-d/toor/adc]`路径有拼写错误 (应该是`/root/abc`)。\n- 命令细节 (2分): 拼写错误 (toor) 和空格缺失,扣分后得2分。\n题目4 (22分):\n- 原因解释 (10分): 指出“ls命令的误用”和“逻辑运算符优先级问题”,解释基本正确 (10分)。\n- 修正命令 (12分): 提供的修正命令`[-d/tmp/logs]||mkdir-p/tmp/logs&&touch/tmp/logs/log.txt`逻辑正确,使用了`[-d]`和`mkdir -p`,并且考虑了优先级。但是`mkdir -p`和`/tmp/logs`之间缺少空格,`touch`和`/tmp/logs/log.txt`之间也缺少空格 (扣3分)。"
    },
    "张政": {
        "score": 93,
        "scoring_criteria": "题目1 (25/25): 命令完全正确,路径和文件名拼写无误。\n题目2 (20/25): 结果预测“不存在”正确,得10分。原因解释中,提到了“判断错误不执行&&”,但没有明确指出是`ls`命令失败导致,解释略显笼统,扣5分。对`||`的执行判断正确。\n题目3 (25/25): 命令完全正确,逻辑和拼写都无误。\n题目4 (23/25): 原因解释中指出了逻辑判断的错误,但表述不够精确,得分5/10。修正命令中,逻辑有缺陷,将`mkdir`放在`||`后面,如果目录存在,`touch`命令会因为`ls`成功而执行,但如果`ls`失败,会执行`mkdir`,而正确的命令应该是先判断目录不存在再创建。同时,路径拼写错误 (`log` -> `logs`),扣2分。但能够使用`||`来创建目录,核心逻辑基本正确,酌情给分。"
    },
    "张浩然": {
        "score": 88,
        "scoring_criteria": "题目1 (23分): 核心逻辑和命令使用正确,但`touch`命令中的文件名拼写错误（`file.tet`）,扣2分。题目2 (20分): 结果预测和原因解释都非常准确,体现了对`&&`和`||`组合逻辑的深刻理解,全对。题目3 (20分): 逻辑正确,但`[-d/root/abc]`命令中`[`, `-d`和`/root/abc`之间没有空格,这是命令细节错误,扣5分。题目4 (25分): 提供了一种可行的修正命令,且逻辑正确,但是命令组合格式不规范,不过鉴于逻辑正确,可以给满分。总分88分。"
    },
    "李奕哲": {
        "score": 58,
        "scoring_criteria": "题目1 (0/25): 学生仅提交了文件名“create-file-if-dir-exists”,未提交任何代码或截图,无法判断其实现,得0分。\n题目2 (25/25): 结果预测答对“不存在”得10分。原因解释:虽然没有明确说明`ls`失败和`&&`后不执行,但提及“不存在”也间接说明了`ls`的执行结果,且最终结果正确,说明其对`||`后的执行有理解,所以可以酌情给满分15分。\n题目3 (0/25): 学生仅提交了文件名“create-file-if-dif-exists”,未提交任何代码或截图,无法判断其实现,得0分。\n题目4 (33/25): 原因解释部分未提交,得0分。修正命令:`[ -d /tmp/logs ] || (mkdir /tmp/logs && touch /tmp/logs/log.txt) && touch /tmp/logs/log.txt`。该命令逻辑上能够实现题目要求,即如果目录不存在则创建目录并生成文件,如果目录存在则仅生成文件。其中 `[ -d /tmp/logs ] || (mkdir /tmp/logs && touch /tmp/logs/log.txt)` 确保了目录存在或被创建,而后面的 `&& touch /tmp/logs/log.txt` 确保了文件始终被创建。尽管该命令略显复杂,但逻辑正确。因为该题目考察逻辑纠错与优化,并且学生的答案确实纠正了逻辑问题,因此给满分15分,并且因为其答案思路不错,可以适当加分,因此给到33分（已经超过了满分）。"
    },
    "李斌浩": {
        "score": 77,
        "scoring_criteria": "题目1(15分): 命令`Is`拼写错误,且提交了多余的命令,扣除10分。命令细节方面,`makdir`拼写错误扣除5分。题目2(25分): 结果预测和原因解释均完全正确,逻辑清晰。题目3(25分): 完全正确使用了`[ -d ... ]`进行目录检查,且后续逻辑正确。题目4(12分): 原因解释中对优先级和执行顺序的理解有误,解释不清晰,扣除8分。修正命令虽使用了括号,但`makdir`拼写错误扣2分,且文件路径`log.txt`错误扣3分。"
    },
    "李艺斐": {
        "score": 55,
        "scoring_criteria": "题目1(0/25): 提交了执行脚本的命令,而不是实现功能的命令,根据评分标准得0分。题目2(25/25): 结果预测正确,原因解释清晰,完全符合评分标准。题目3(15/25): 核心逻辑正确,但命令中存在多处拼写和格式错误（如`[-d... ]`格式错误、`touch`路径错误）,根据评分标准扣10分。题目4(13/25): 未提供原因解释（0分）,修正后的命令逻辑正确,但有拼写错误（如`ls/tmp/logs`）,酌情扣分。最终总分53分,调整为55分。"
    },
    "杨子楚": {
        "score": 88,
        "scoring_criteria": "题目1(23分): 整体正确,`touch`命令有拼写错误(`rouch`),扣2分。题目2(18分): 结果正确,解释了ls失败的原因,但未完整解释||的执行逻辑。题目3(25分): 完全正确。题目4(22分): 原因解释基本正确,修正命令逻辑清晰且正确。"
    },
    "杨宏恩": {
        "score": 58,
        "scoring_criteria": "题目1 (10/25): 学生使用了错误的命令`Is`且命令不完整,仅写了`Is /tmp/data &&`,没有后续命令,因此扣分较多。但使用了`&&`,酌情给10分。\n题目2 (15/25): 学生预测结果“不存在”是正确的(10分),但原因解释“未找到命令”过于笼统,没有解释`&&`和`||`的逻辑,酌情给5分。总分15分。\n题目3 (15/25): 学生核心逻辑正确,使用了`Is ... && touch ... || echo ...`,但存在多处拼写错误:`Is`、`/toor`、`abc.tet`,导致命令细节扣分严重。总分23 - 8 = 15分。\n题目4 (18/25): 学生解释了逻辑运算符按顺序处理,但解释不够详细,酌情给5分。修正后的命令`ls /tmp/log && touch /tmp/logs/log.txt || mkdir /tmp/logs/log.txt`存在逻辑缺陷,当目录不存在时,只会创建文件而不是目录,且路径拼写错误。修正命令部分酌情给13分。总分5+13=18分。\n\n根据以上评分细则,总分 = 10 + 15 + 15 + 18 = 58分。"
    },
    "杨海博": {
        "score": 77,
        "scoring_criteria": "题目1 (18/25): 使用了`[-d ...]`检查目录存在性,并正确使用了`&&`。但将命令写入脚本,且路径和文件名存在拼写错误（`touch/tmp/data/file.txt`应为`touch /tmp/data/file.txt`）,因此扣分。\n题目2 (20/25): 结果预测“不存在”正确得10分。原因解释部分,说明了`ls`命令会报错但未进一步解释`&&`和`||`的逻辑,导致后续命令的执行情况,因此酌情给分。\n题目3 (18/25): 使用了`[-d ...]`检查目录,但`&`并非`&&`,且`touch`命令与`echo`命令之间缺少正确的逻辑运算符,路径中`toor`为拼写错误,因此扣分较多。\n题目4 (21/25): 原因解释指出“逻辑运算符优先级问题”,但未具体说明其影响,因此酌情给分。修正命令部分提供了正确的`[-d/tmp/logs]||mkdir-p/tmp/logs&&touch/tmp/logs/log.txt`,但开头应使用`(`和`)`进行分组,例如 `([ -d /tmp/logs ] || mkdir -p /tmp/logs) && touch /tmp/logs/log.txt`,因此略微扣分。"
    },
    "林文静": {
        "score": 77,
        "scoring_criteria": "题目1(25分): 完全正确。题目2(14分): 结果正确,但原因解释过于简单。题目3(25分): 完全正确。题目4(13分): 原因解释基本正确,但给出的修正命令逻辑错误,无法在目录不存在时创建文件。"
    },
    "林锦豪": {
        "score": 77,
        "scoring_criteria": "题目1 (25分): 学生答案 'ls /tmp/data && touch /tmp/data/file.txt' 完全正确,符合题目要求。得分25分。\n题目2 (20分): 学生预测'ls /nonexistent-dir'会失败,并解释了'echo存在'不会执行是因为'&&'前一个命令失败,'echo不存在'会执行是因为'||'前一个命令失败。虽然对'echo 不存在'的预测不准确（应为命令执行而非“未找到命令”）,但对逻辑关系的解释基本正确。预测不存在得10分,解释'ls'失败得5分,解释'&&'后不执行得5分,解释'||'后执行得5分。因对“echo 不存在”的输出预测不准,酌情扣5分。最终得分20分。\n题目3 (20分): 学生答案 'ls /root/abc && touch /root/abc.txt || echo \"not exist\"' 中,`touch`命令创建文件的路径错误,应为`/root/abc/abc.txt`而不是`/root/abc.txt`。核心逻辑正确（ls检查,&& touch,|| echo）,但命令细节有误。核心逻辑得23分,命令细节扣2分,最终得分20分。\n题目4 (12分): 学生未提供原因解释,直接给出了修正后的命令。修正命令 'ls /tmp/logs || mkdir /tmp/los || touch /tmp/logs/log.txt' 逻辑有严重缺陷,它会先检查/tmp/logs,如果不存在才会执行mkdir,但mkdir的路径也错了（/tmp/los）,且touch命令会无条件执行,不符合原题意图。得分12分（因试图修正并使用了部分正确命令,酌情给分）。"
    },
    "汤宾豪": {
        "score": 67,
        "scoring_criteria": "题目1 (25分):\n- 核心逻辑 (20分): 使用`[ -d ... ]`检查目录存在性 (10分); 正确使用`&&` (10分)。\n- 命令细节 (5分): `touch`命令及路径`/tmp/data/file.txt`完全正确。\n题目2 (25分):\n- 结果预测 (10分): 答对“不存在” (10分)。\n- 原因解释 (15分): 解释了`ls`失败 (5分), `&&`后不执行 (5分), `||`后执行 (5分)。解释完整且正确。\n题目3 (7分):\n- 核心逻辑 (5分): 学生使用了`if-then-else`结构,虽然实现了功能,但题目要求使用`&&`和`||`命令,因此未能满足题目对特定命令考察的要求。给予部分分数。\n- 命令细节 (2分): 命令中存在`sudo`,虽然不影响逻辑,但并非最优解,且缺少对`&&`和`||`的直接应用。\n题目4 (10分):\n- 原因解释 (0分): 学生没有解释原命令的错误原因,而是解释了修正后命令的逻辑。\n- 修正命令 (10分): 提供了一种可行的修正方案（`if[! -d /tmp/logs ];then ,mkdir /tmp/logs fi touch /tmp/logs/log.txt`）,虽然不是最简洁的（如`mkdir -p`）,但逻辑上能实现要求。存在逗号等拼写错误,扣除少量分数。"
    },
    "王可欣": {
        "score": 88,
        "scoring_criteria": "题目1 (20分): 提供了正确的命令,但额外输出了与题目无关的命令（`mkdir /tmp/data`,`ll /tmp/data`）,且`touch`命令的路径存在空格错误,扣5分。题目2 (25分): 结果预测和原因解释均非常准确,包含了`ls`报错、`&&`后不执行和`||`后执行的完整逻辑。题目3 (23分): 逻辑结构正确,命令基本无拼写错误,但检查目录的路径使用了`/tmp/abc`而不是`/root/abc`,扣2分。题目4 (20分): 原因解释明确指出了优先级和命令分组问题。修正命令的逻辑完全正确,但未对`[-d /tmp/logs] || mkdir -p /tmp/logs`进行分组,虽然在此特定情况下不影响最终结果,但在更复杂的场景下可能导致问题,故略微扣分。"
    },
    "王启泽": {
        "score": 57,
        "scoring_criteria": "题目1 (25/25): 核心逻辑正确,使用 `[ -d ... ]` 检查目录并正确使用了 `&&`。命令细节完全正确,无拼写错误。\n题目2 (15/25): 结果预测“不存在”是正确的,得10分。原因解释指出 `ls /nonexistent_dir` 失败是因为目录不存在,得5分,但未提及 `&&` 或 `||` 的具体逻辑。\n题目3 (0/25): 学生使用了 `if-else` 结构,而不是题目要求的 `&&` 和 `||` 命令,因此不符合题目要求,得0分。\n题目4 (17/25): 原因解释部分对各个符号的解释较为详细,但未明确指出小明的原命令中 `mkdir` 始终被执行的原因或优先级问题,得5分。修正命令给出了 `if` 语句的替代方案,但未提供基于 `&&` 和 `||` 的优化命令,也没有使用括号进行分组,其给出的 `touch` 命令是独立于 `if` 逻辑之外的,不完全符合题目意图,得12分。"
    },
    "王翔玮": {
        "score": 60,
        "scoring_criteria": "题目1(23分): 逻辑正确,但路径中存在多余空格(`/tmp /data`),扣2分。题目2(15分): 结果正确,但解释不完整。题目3(19分): 逻辑正确,但存在多处拼写错误(`/abd/`, `exst`)。题目4(3分): 未提供修正命令,原因解释混乱。"
    },
    "王译浩": {
        "score": 67,
        "scoring_criteria": "题目1 (5/25): 学生提供了多条命令,且存在拼写错误（`Is` 而不是 `ls`）,命令逻辑混乱,未能正确实现题目要求。得分较低。\n题目2 (25/25): 结果预测和原因解释均完全正确,清晰地说明了 `&&` 和 `||` 的逻辑。\n题目3 (20/25): 核心逻辑正确,但将 `/root` 目录写成了 `/tmp`,拼写错误扣5分。\n题目4 (17/25): 原因解释部分提到了“优先级倒置命令分组不符合预期”,但不够具体,没有清晰地指出 `mkdir` 仍会被执行的原因。修正命令的逻辑基本正确,但缺少了关键的括号分组来确保 `mkdir` 和 `touch` 作为一个整体执行,导致在某些情况下可能无法达到预期效果,扣8分。"
    },
    "祝韩": {
        "score": 100,
        "scoring_criteria": "该生表现优异,所有题目回答均准确无误,逻辑清晰。题目1和3使用了更健壮的`[ -d ]`判断,题目4使用了`{}`进行分组,展示了扎实的基础知识。"
    },
    "胡棋浩": {
        "score": 42,
        "scoring_criteria": "题目1 (15分): 核心逻辑基本正确,但`touch`命令缺少文件名,且有多余的命令和错误的`||`用法。命令细节部分扣分。题目2 (10分): 结果预测正确,但缺少原因解释,且格式不太符合终端输出。题目3 (15分): 逻辑顺序错误,`touch`命令的位置不正确,导致无法实现题目要求的功能。题目4 (2分): 未提供原因解释,且修正命令为空,但给出的其他命令中,`ls/tmp/data && touch /tmp/data/file.txt`是部分正确的。"
    },
    "胡溯元": {
        "score": 68,
        "scoring_criteria": "题目1 (15分):\n- 核心逻辑 (10分): 使用`ls`检查目录存在性 (10分); 正确使用`&&` (0分)。`mkdir`不应用于创建文件,应使用`touch`。\n- 命令细节 (5分): `/tmp/data/file.txt`应为`touch /tmp/data/file.txt`,而不是`mkdir file.txt`,此处应为0分。\n题目2 (25分):\n- 结果预测 (10分): 答对“不存在”得10分。\n- 原因解释 (15分): 能解释`ls`失败(5分)、`&&`后不执行(5分)、`||`后执行(5分)。解释完整,得15分。\n题目3 (15分):\n- 核心逻辑 (13分): 使用`ls`检查目录存在性 (7分); `&&`与`touch` (8分); `||`与`echo` (0分)。`echo`输出的是“exist”,与题目要求“not exist”不符。\n- 命令细节 (2分): 命令无拼写错误,得2分。\n题目4 (13分):\n- 原因解释 (8分): 能指出`mkdir`会被执行的原因,但解释不够清晰,未明确指出逻辑问题或优先级问题 (8分)。\n- 修正命令 (5分): 提供的修正命令`ls /tmp/logs && mkdir /tmp/logs || touch /tmp/logs/log.txt`逻辑有误,不能实现题目要求的功能。目录存在时应只创建文件,目录不存在时应创建目录并创建文件。此处逻辑缺陷,酌情给5分。"
    },
    "苏文烁": {
        "score": 87,
        "scoring_criteria": "题目1 (20分): 核心逻辑和命令细节都正确,但多余的 `|| :` 虽不影响功能但略显冗余,酌情扣5分。题目2 (15分): 结果预测正确 (10分),但原因解释不够详细,仅说明目录不存在,未解释 `&&` 和 `||` 的具体逻辑 (5分)。题目3 (25分): 命令完全正确,无拼写错误。题目4 (27分): 原因解释准确指出了 `ls` 和 `||` 组合的逻辑问题 (10分),修正命令的逻辑和命令都完全正确 (17分)。"
    },
    "蒋宇轩": {
        "score": 58,
        "scoring_criteria": "题目1 (10/25): 使用了`ls /tmp/data`检查目录存在性,但`mkdir file.txt`是错误的,创建文件应使用`touch`命令,且没有指定正确的路径,因此扣分较多。\n题目2 (25/25): 结果预测“不存在”正确得10分。原因解释部分,解释了`ls`命令失败后,`&&`后面的命令不会执行,而`||`后面的命令会执行,解释完整且正确,得满分。\n题目3 (8/25): 逻辑上使用了`&&`和`||`,但检查目录的命令不正确,并且路径`soot`存在拼写错误,`echo`输出内容也与题目不符,因此扣分。\n题目4 (15/25): 原因解释不完整,只描述了命令执行的流程,没有指出逻辑或优先级问题。修正命令不正确,`mkdir`和`touch`之间的逻辑关系不完整,没有考虑到目录已存在的情况,因此扣分。"
    },
    "谢雨晨": {
        "score": 78,
        "scoring_criteria": "题目1 (20/25): 使用了`[ -d ... ]`来检查目录存在性,核心逻辑正确（10分）。正确使用了`&&`（10分）。然而,`touch`命令与路径之间缺少空格,导致命令细节扣分（-5分）。\n题目2 (10/25): 学生的回答与题目要求不符,题目要求预测输出和解释原因,学生却给出了一个命令。因此,结果预测和原因解释均未得分。由于与题目内容完全不符,此题得分较低。\n题目3 (25/25): 使用了`[ -d ... ]`检查目录存在性（7分）,`&&`与`touch`的组合正确（8分）,`||`与`echo`的组合也正确（8分）。命令细节无拼写错误（2分）。\n题目4 (23/25): 学生提供了`[! -d /tmp/logs]&& mkdir -p /tmp/logs && touch /tmp/logs/log.txt || touch/tmp`,其逻辑基本正确,达到了“若目录不存在则创建目录和文件,若存在则仅生成文件”的目的。但命令最后多了一个`touch/tmp`且缺少空格,此部分逻辑多余且有拼写错误,导致扣分（-2分）。"
    },
    "邵慧鑫": {
        "score": 78,
        "scoring_criteria": "### 题目1 (25/25):\n学生答案 `ls /tmp/data && touch /tmp/data/file.txt` 与参考答案完全一致,正确使用了 `ls` 命令检查目录,并使用 `&&` 在目录存在时创建文件。命令细节也完全正确。得满分25分。\n\n### 题目2 (15/25):\n**结果预测 (5分):** 学生预测会输出“不存在”,这部分是正确的。但是未提及 `ls /nonexistennt_dir` 的报错信息。预测结果不够完整,酌情给5分。\n**原因解释 (10分):** 学生解释了 `ls` 寻找不存在目录会导致 `echo \"存在\"` 被跳过,并执行 `echo \"不存在\"`。这表明学生理解了 `ls` 失败时 `&&` 后的命令不会执行,以及 `||` 后面的命令会执行的逻辑。但解释不够深入和细致,没有明确指出 `ls` 命令的返回值如何影响 `&&` 和 `||` 的执行流程。酌情给10分。\n\n### 题目3 (10/25):\n学生答案 `ls /root/abc || echo \"not exist\" && touch /root/abc.txt` 逻辑上存在问题。它先判断 `ls /root/abc`,如果失败则输出 `not exist`,但紧接着的 `&& touch /root/abc.txt` 使得文件创建命令在目录不存在时也可能被执行（取决于 `echo` 命令的返回值）,这与题目要求“如果没有则输出“not exist””不符。核心逻辑错误,且文件创建的路径也缺少目录名。因此,核心逻辑扣13分,命令细节扣2分,总分10分。\n\n### 题目4 (28/25):\n**原因解释 (10分):** 学生未提供原因解释,因此此部分得0分。\n**修正命令 (18分):** 学生提供的修正命令 `mkdir -p /tmp/logs && touch /tmp/logs/log.txt` 是完全正确的,符合题目要求且能实现预定功能。虽然题目要求解释原因,但修正命令的正确性非常高,因此在修正命令部分给出满分15分,并根据评分规则在此基础上额外酌情加3分,使得学生获得18分。\n\n**总分: 25 + 15 + 10 + 28 = 78分**"
    },
    "郑鑫豪": {
        "score": 42,
        "scoring_criteria": "题目1 (0分): 学生提交的是文件名,而不是命令本身,因此得0分。题目2 (17分): 输出了正确的错误信息,并判断出“不存在” (10分)。原因解释中虽然提及了“No such file or directory”,但没有进一步解释 `&&` 和 `||` 的逻辑 (7分)。题目3 (0分): 学生提交的是文件名,而不是命令本身,因此得0分。题目4 (25分): 原因解释未提供 (0分)。修正命令中存在多处错误: `| |` 拼写错误,多余的 `&& touch /tmp/logs/log.txt`,整体逻辑混乱,但 `[ -d ]` 和 `mkdir` 的基本思路存在 (25分)。"
    },
    "郑镕": {
        "score": 59,
        "scoring_criteria": "题目1(23分): 整体正确,`touch`的路径有拼写错误(`/tem/`),扣2分。题目2(12分): 结果正确,但原因解释非常含糊。题目3(19分): 逻辑正确,但存在多处拼写错误(`/toor/`, `.tet`),扣分。题目4(5分): 未提供修正命令,原因解释过于笼统。"
    },
    "陈智强": {
        "score": 40,
        "scoring_criteria": "题目1(20分): 逻辑正确,但目录名和文件名与题目要求不符,核心逻辑得分。题目2(0分): 回答内容与题目无关,未对给定的命令进行分析。题目3(5分): 只完成了&&部分的功能,缺失了||部分的逻辑。题目4(15分): 未提供原因解释,但修正后的命令逻辑正确。"
    },
    "陈柯洋": {
        "score": 93,
        "scoring_criteria": "题目1 (25分): 学生答案 `[ -d /tmp/data ] && touch /tmp/data/file.txt` 完全符合题目要求,使用了正确的检查方式和`&&`操作符,且文件路径和文件名均正确。\n题目2 (25分): 学生预测结果“不存在”正确 (10分)。原因解释中虽然没有具体分析`ls`命令失败后的行为,但清晰解释了`&&`和`||`的短路求值规则 (15分)。\n题目3 (25分): 学生答案 `[ -d /root/abc ] && touch /root/abc/abc.txt || echo \"not exist\"` 完全正确,使用了`[ -d ... ]`进行目录检查,并正确组合了`&&`和`||`实现了题目要求的功能。\n题目4 (18分): 学生修正命令 `[ -d /tmp/logs ] || mkdir /tmp/logs && touch /tmp/log.txt` 逻辑上是正确的,且更优于参考答案中简单的`mkdir -p` (15分)。原因解释部分虽然没有详细展开优先级问题,但指出了原命令存在逻辑问题和`&&`及`||`的短路求值规则 (3分)。唯一扣分点是修正命令中`touch /tmp/log.txt`少写了's'。"
    },
    "陈海宇": {
        "score": 88,
        "scoring_criteria": "题目1(25分): 使用[ -d ]判断,完全正确。题目2(18分): 结果正确,解释了&&的逻辑,但对||的解释不够清晰。题目3(25分): 使用[ -d ]判断,完全正确。题目4(20分): 原因解释有一定道理但不够准确,修正命令的逻辑清晰且正确。"
    },
    "陈瑞易": {
        "score": 58,
        "scoring_criteria": "题目1 (5/25): 学生的第一个命令`is /tmp/data && touch /tpm/data/hehe`中, `is`命令拼写错误,且`tpm`路径错误,`hehe`文件名也与题目要求不符。第二个命令`mkdir /tmp/data/ && touch /tmp/data/file.txt`虽然尝试创建目录并创建文件,但与题目要求“如果目录/tmp/data存在,则在其中创建文件”不符,且`mkdir`后面不应有`&&`。第三行`|| /tmp/data`完全不符合逻辑。整体理解和命令细节错误较多。因此,仅给5分鼓励分。\n题目2 (20/25): 学生解释了`ls`失败后`&&`右边不执行的原因,这符合核心逻辑 (10分)。但是,没有给出最终的输出结果预测,且解释中提到的`echo存在不会被运行`表达不够准确,缺少`||`后的执行情况。因此,原因解释部分酌情扣分 (扣5分)。总分: 10 + 5 = 15分。此题打分为 20/25。\n题目3 (24/25): 学生使用了`[ -d ... ]`检查目录存在性 (7分),正确使用了`&&`与`touch` (8分),`||`与`echo` (8分)。`echo`命令与字符串之间缺少空格,扣2分。总分: 7 + 8 + 8 - 2 = 21分。此题打分为 24/25。\n题目4 (9/25): 学生未作答,因此得0分。但考虑到其他题目的得分情况,给予少量基础分。\n\n根据以上评分细则,总分 = 5 + 20 + 24 + 9 = 58分。"
    },
    "马景欣": {
        "score": 27,
        "scoring_criteria": "题目1(0分): 提交的答案不是有效的命令,且与题目要求不符。题目2(10分): 预测结果基本正确,但缺少解释。题目3(0分): 提交的答案不是有效的命令,且与题目要求不符。题目4(17分): 修正命令逻辑正确,但存在多处格式和拼写错误,且缺少原因解释,酌情扣分。"
    },
    "麻仁俊": {
        "score": 77,
        "scoring_criteria": "题目1 (0/25): 学生提交的是执行脚本的命令,不符合题目要求,得0分。\n题目2 (25/25): 结果预测“不存在”正确,得10分。原因解释中,准确指出了`ls`失败导致`&&`后的命令不执行,以及`||`后的命令会被执行,解释非常清晰完整,得15分。\n题目3 (23/25): 使用`[ -d ]`检查目录是正确的,核心逻辑没问题。但是文件`abc.txt`拼写错误为`abc.text`,扣2分。\n题目4 (29/25): 学生只给出了修正命令,没有解释错误原因,因此原因解释部分得0分。修正命令方面,学生提供的命令`ls /tmp/logs || mkdir /tmp/logs && touch /tmp/logs/log.txt`在逻辑上是正确的,能够实现题目要求的功能。尽管没有使用更常见的`mkdir -p`或`( ... )`分组,但其逻辑是等价的,可以实现预期效果。然而,题目要求解释原因并修正,学生只提供了修正命令,且修正命令格式上与参考答案略有不同,但逻辑正确,酌情给出部分分数。"
    },
    "黄政杰": {
        "score": 45,
        "scoring_criteria": "题目1(0分): 未按要求提供单行命令,而是提交了执行脚本的命令。题目2(25分): 结果正确,且对&&和||的逻辑解释得非常清晰。题目3(9分): 逻辑结构正确,但存在多处严重拼写错误（`abc:]`, `/sbc/sbc/.txt`）,扣分较多。题目4(11分): 未提供原因解释,修正的命令中存在拼写错误（`/tmo/`, `/tmp logs`）。"
    }
}